volatile_dictionary/__init__.py
volatile_dictionary/volatile_dict.py
volatile_dictionary-0.1.dist-info/METADATA
volatile_dictionary-0.1.dist-info/WHEEL
volatile_dictionary-0.1.dist-info/top_level.txt
volatile_dictionary-0.1.dist-info/RECORD
