Metadata-Version: 2.1
Name: volatile-dictionary
Version: 0.1
Summary: An extension of python's native dictionary class, that implements volatile sets.
Home-page: https://github.com/pedrogyrao/volatile_dictionary
Author: gyrao
Author-email: pedrogyrao@hotmail.com
License: MIT
Platform: UNKNOWN
Classifier: Programming Language :: Python :: 3
Classifier: License :: OSI Approved :: MIT License
Classifier: Operating System :: OS Independent
Requires-Dist: apscheduler
